[{"title": "Dk-behrt: Teaching language models international classification of disease (icd) codes using known disease descriptions", "link": "https://proceedings.mlr.press/v281/an25a", "details": "U An, SA Lee, M Jeong, A Gorla, JN Chiang\u2026 - AAAI Bridge Program on AI \u2026, 2025", "abstract": "The widespread digitization of healthcare and patient data has created new opportunities to explore machine learning techniques for improving patient care. The sheer scale of this data has particularly motivated the use of deep learning methods \u2026"}, {"title": "Social determinants of health extraction from clinical notes across institutions using large language models", "link": "https://www.nature.com/articles/s41746-025-01645-8", "details": "VK Keloth, S Selek, Q Chen, C Gilman, S Fu, Y Dang\u2026 - npj Digital Medicine, 2025", "abstract": "Detailed social determinants of health (SDoH) is often buried within clinical text in EHRs. Most current NLP efforts for SDoH have limitations, investigating limited factors, deriving data from a single institution, using specific patient cohorts/note \u2026"}]
