[{"title": "UniverDetect: Universal Landmark Detection Method for Multidomain X-ray Images", "link": "https://www.sciencedirect.com/science/article/pii/S0925231224009287", "details": "C Lu, G Yang, X Qiao, W Chen, Q Zeng - Neurocomputing, 2024", "abstract": "Landmark detection using X-ray imaging is vital for disease screening, treatment, and prognosis. It provides a framework for subsequent tasks, including segmentation, classification, and target detection. Existing landmark detection \u2026"}, {"title": "SAM2CLIP2SAM: Vision Language Model for Segmentation of 3D CT Scans for Covid-19 Detection", "link": "https://arxiv.org/pdf/2407.15728", "details": "D Kollias, A Arsenos, J Wingate, S Kollias - arXiv preprint arXiv:2407.15728, 2024", "abstract": "This paper presents a new approach for effective segmentation of images that can be integrated into any model and methodology; the paradigm that we choose is classification of medical images (3-D chest CT scans) for Covid-19 detection. Our \u2026"}]
