[{"title": "A Multimodal Knowledge-enhanced Whole-slide Pathology Foundation Model", "link": "https://arxiv.org/pdf/2407.15362", "details": "Y Xu, Y Wang, F Zhou, J Ma, S Yang, H Lin, X Wang\u2026 - arXiv preprint arXiv \u2026, 2024", "abstract": "Remarkable strides in computational pathology have been made in the task-agnostic foundation model that advances the performance of a wide array of downstream clinical tasks. Despite the promising performance, there are still several challenges \u2026"}, {"title": "STORYSUMM: Evaluating Faithfulness in Story Summarization", "link": "https://arxiv.org/pdf/2407.06501", "details": "M Subbiah, F Ladhak, A Mishra, G Adams, LB Chilton\u2026 - arXiv preprint arXiv \u2026, 2024", "abstract": "Human evaluation has been the gold standard for checking faithfulness in abstractive summarization. However, with a challenging source domain like narrative, multiple annotators can agree a summary is faithful, while missing details \u2026"}]
