[{"title": "Practical Guide to Image-Based Big Data Research", "link": "https://jamanetwork.com/journals/jamasurgery/article-abstract/2828664", "details": "EG Ross, S Arya, ML Melcher - JAMA surgery, 2025", "abstract": "Imaging is a cornerstone of modern surgical care. Computed tomography (CT) allows us to quickly diagnose a ruptured aortic aneurysm, 4K high-definition laparoscopes enable laparoscopic and robotic surgeries, and digital histopathology \u2026"}, {"title": "Personalized Photoprotection: Expert Consensus and Recommendations From a Delphi Study Among Dermatologists", "link": "https://pmc.ncbi.nlm.nih.gov/articles/PMC11771696/", "details": "M de Troya\u2010Mart\u00edn, A Rodr\u00edguez\u2010Mart\u00ednez\u2026 - Photodermatology \u2026, 2025", "abstract": "Background Recommending comprehensive personalized photoprotection requires an accurate assessment of the patient's skin, including phototype, lifestyle, exposure conditions, environmental factors, and concomitant cutaneous conditions as well as \u2026"}]
